asfsmd/__init__.py
asfsmd/__main__.py
asfsmd/_utils.py
asfsmd/cli.py
asfsmd/common.py
asfsmd/core.py
asfsmd/fsspec_client.py
asfsmd/httpio_client.py
asfsmd/remotezip_client.py
asfsmd/smart_open_client.py
asfsmd-1.4.1.dist-info/LICENSE
asfsmd-1.4.1.dist-info/METADATA
asfsmd-1.4.1.dist-info/WHEEL
asfsmd-1.4.1.dist-info/entry_points.txt
asfsmd-1.4.1.dist-info/top_level.txt
asfsmd-1.4.1.dist-info/zip-safe
asfsmd-1.4.1.dist-info/RECORD
