Metadata-Version: 2.1
Name: asfsmd
Version: 1.4.1
Summary: ASF Sentinel-1 Metadata Download tool
Author-email: Antonio Valentino <antonio.valentino@tiscali.it>
License: MIT License
Project-URL: Homepage, https://github.com/avalentino/asfsmd
Project-URL: Documentation, https://github.com/avalentino/asfsmd/blob/main/README.rst
Project-URL: Repository, https://github.com/avalentino/asfsmd.git
Project-URL: Changelog, https://github.com/avalentino/asfsmd/blob/main/CHANGELOG.rst
Keywords: satellite,download
Classifier: Development Status :: 4 - Beta
Classifier: Intended Audience :: Science/Research
Classifier: License :: OSI Approved :: MIT License
Classifier: Programming Language :: Python :: 3
Classifier: Programming Language :: Python :: 3 :: Only
Classifier: Topic :: Scientific/Engineering
Classifier: Topic :: Utilities
Requires-Python: >=3.7
License-File: LICENSE
Requires-Dist: fsspec
Requires-Dist: aiohttp
Requires-Dist: asf-search
Requires-Dist: tqdm
Requires-Dist: asf-search <6 ; python_version < "3.8"
Provides-Extra: all
Requires-Dist: asfsmd[cli] ; extra == 'all'
Requires-Dist: asfsmd[httpio] ; extra == 'all'
Requires-Dist: asfsmd[remotezip] ; extra == 'all'
Requires-Dist: asfsmd[smartopen] ; extra == 'all'
Provides-Extra: cli
Requires-Dist: argcomplete ; extra == 'cli'
Provides-Extra: httpio
Requires-Dist: httpio ; extra == 'httpio'
Requires-Dist: requests ; extra == 'httpio'
Provides-Extra: remotezip
Requires-Dist: remotezip ; extra == 'remotezip'
Provides-Extra: smartopen
Requires-Dist: smart-open ; extra == 'smartopen'
